googlevoice/__init__.py
googlevoice/__main__.py
googlevoice/conf.py
googlevoice/interact.py
googlevoice/settings.py
googlevoice/setup-asterisk.py
googlevoice/test_all.py
googlevoice/util.py
googlevoice/voice.py
googlevoice-3.1.1.dist-info/LICENSE
googlevoice-3.1.1.dist-info/METADATA
googlevoice-3.1.1.dist-info/WHEEL
googlevoice-3.1.1.dist-info/top_level.txt
googlevoice-3.1.1.dist-info/RECORD
